{
  "project_info": {
    "project_number": "788164346630",
    "project_id": "make-it-native-test",
    "storage_bucket": "make-it-native-test.appspot.com"
  },
  "client": [
    {
      "client_info": {
        "mobilesdk_app_id": "1:788164346630:android:8abda4292fe590982d1487",
        "android_client_info": {
          "package_name": "com.mendix.developerapp.mx10"
        }
      },
      "oauth_client": [],
      "api_key": [
        {
          "current_key": "AIzaSyD3pLyuEY38P44jR1hHYr00qKwOL_kJm_k"
        }
      ],
      "services": {
        "appinvite_service": {
          "other_platform_oauth_client": []
        }
      }
    }
  ],
  "configuration_version": "1"
}